{"currentTotalOccupancy":0.9401282965074839629365645046,"currentPMROccupancy":0.1515151515151515151515151515,"currentECarOccupancy":0.8888888888888888888888888889,"openingHours":null,"typeOfAccess":null,"currentTotalFreeSpaces":84,"currentPMRFreeSpaces":28,"currentECarFreeSpaces":6,"totalPMRCapacity":33,"totalECarCapacity":54,"id":"YAX3J","name":"Belval","address":{"streetAndNumber":"226, route de Belval ","city":"Belval","zipCode":"L-4024"},"totalCapacity":1403,"wgS84Coordinate":{"longitude":5.944946,"latitude":49.499393}}